instances_map_abc/__init__.py
instances_map_abc/vm_instance_mapping.py
instances_map_abc/vm_instance_proxy.py
instances_map_abc-1.0.3.dist-info/LICENSE.md
instances_map_abc-1.0.3.dist-info/WHEEL
instances_map_abc-1.0.3.dist-info/METADATA
instances_map_abc-1.0.3.dist-info/RECORD
